./.gitignore
./CLAUDE.md
./LICENSE
./PKG-INFO
./README.md
./main.py
./pyproject.toml
./uv.lock
./.claude/settings.local.json
./build-tools/__init__.py
./build-tools/pyinstaller-hooks/README.md
./build-tools/pyinstaller-hooks/__init__.py
./build-tools/pyinstaller-hooks/hook-ffmpeg.py
./build-tools/pyinstaller-hooks/pyi_rth_ffmpeg.py
./resources/Funded_by_EU_Eyes4ICU.png
./resources/app.png
./resources/app_icon.icns
./resources/app_icon.ico
./resources/giraffe.png
./resources/icons/add_circle.svg
./resources/icons/arrow_down.svg
./resources/icons/arrow_up.svg
./resources/icons/chevron_left.svg
./resources/icons/chevron_right.svg
./resources/icons/delete.svg
./resources/icons/edit.svg
./resources/icons/mark_end.svg
./resources/icons/mark_start.svg
./resources/icons/mute.svg
./resources/icons/pause.svg
./resources/icons/play.svg
./resources/icons/save.svg
./resources/icons/volume.svg
./resources/icons/warning.svg
./zarafe/__init__.py
./zarafe/main_window.py
./zarafe/controllers/__init__.py
./zarafe/controllers/main_controller.py
./zarafe/controllers/project_controller.py
./zarafe/controllers/video_navigation_controller.py
./zarafe/core/__init__.py
./zarafe/core/audio_manager.py
./zarafe/core/color_theme_manager.py
./zarafe/core/config.py
./zarafe/core/configuration_service.py
./zarafe/core/event_manager.py
./zarafe/core/event_type_registry.py
./zarafe/core/gaze_data.py
./zarafe/core/shortcut_manager.py
./zarafe/core/video_manager.py
./zarafe/utils/__init__.py
./zarafe/utils/ffmpeg_compat.py
./zarafe/utils/file_utils.py
./zarafe/utils/icon_loader.py
./zarafe/utils/importer.py
./zarafe/utils/sorting.py
./zarafe/utils/theme.py
./zarafe/utils/aria/__init__.py
./zarafe/utils/aria/aria_importer.py
./zarafe/utils/aria/aria_vrs_exporter.py
./zarafe/utils/aria/vrs_to_video_lossless.py
./zarafe/widgets/__init__.py
./zarafe/widgets/about_dialog.py
./zarafe/widgets/base_dialog.py
./zarafe/widgets/event_controls.py
./zarafe/widgets/menu_manager.py
./zarafe/widgets/metadata_panel.py
zarafe-2.0.0.dist-info/METADATA
zarafe-2.0.0.dist-info/WHEEL
zarafe-2.0.0.dist-info/entry_points.txt
zarafe-2.0.0.dist-info/licenses/LICENSE
zarafe-2.0.0.dist-info/RECORD
