Metadata-Version: 2.4
Name: zarafe
Version: 2.0.0
Summary: Video annotation tool for marking timed events in eye tracking research
Author-email: Mohammadhossein Salari <mohammadhossein.salari@gmail.com>
License: MIT License
License-File: LICENSE
Requires-Python: >=3.11
Requires-Dist: glassestools==1.23.1
Requires-Dist: moviepy==1.0.3
Requires-Dist: numpy>=2.3.0
Requires-Dist: opencv-python-headless>=4.11.0
Requires-Dist: pandas>=2.3.0
Requires-Dist: projectaria-tools>=2.0.0
Requires-Dist: pyqt6>=6.9.0
Requires-Dist: pyqtgraph>=0.13.7
Requires-Dist: scipy>=1.16.0
Provides-Extra: dev
Requires-Dist: pytest; extra == 'dev'
